pyTSFoil/TSfoil.py
pyTSFoil/__init__.py
pyTSFoil/tsfoil2-modify.f
pyTSFoil/tsfoil2.exe
pyTSFoil-0.1.1.dist-info/LICENSE
pyTSFoil-0.1.1.dist-info/METADATA
pyTSFoil-0.1.1.dist-info/WHEEL
pyTSFoil-0.1.1.dist-info/top_level.txt
pyTSFoil-0.1.1.dist-info/RECORD
